downhill/__init__.py
downhill/adaptive.py
downhill/base.py
downhill/dataset.py
downhill/first_order.py
downhill/util.py
downhill-0.4.0.dist-info/DESCRIPTION.rst
downhill-0.4.0.dist-info/METADATA
downhill-0.4.0.dist-info/RECORD
downhill-0.4.0.dist-info/WHEEL
downhill-0.4.0.dist-info/metadata.json
downhill-0.4.0.dist-info/top_level.txt
