Metadata-Version: 2.0
Name: downhill
Version: 0.4.0
Summary: Stochastic optimization routines for Theano
Home-page: http://github.com/lmjohns3/downhill
Author: Leif Johnson
Author-email: leif@lmjohns3.com
License: MIT
Keywords: adadelta adam esgd gradient-descent nesterov optimization rmsprop sgd theano
Platform: UNKNOWN
Classifier: Development Status :: 4 - Beta
Classifier: Intended Audience :: Science/Research
Classifier: License :: OSI Approved :: MIT License
Classifier: Operating System :: OS Independent
Classifier: Topic :: Scientific/Engineering
Requires-Dist: theano
Requires-Dist: click
